empower_core/__init__.py
empower_core/acl.py
empower_core/app.py
empower_core/appworker.py
empower_core/command.py
empower_core/etheraddress.py
empower_core/eui64.py
empower_core/imsi.py
empower_core/launcher.py
empower_core/plmnid.py
empower_core/serialize.py
empower_core/service.py
empower_core/ssid.py
empower_core/walkmodule.py
empower_core/worker.py
empower_core/accountsmanager/__init__.py
empower_core/accountsmanager/account.py
empower_core/accountsmanager/accountshandler.py
empower_core/accountsmanager/accountsmanager.py
empower_core/apimanager/__init__.py
empower_core/apimanager/apimanager.py
empower_core/cli/__init__.py
empower_core/cli/help_commands/__init__.py
empower_core/cli/help_commands/help.py
empower_core/envmanager/__init__.py
empower_core/envmanager/cataloghandler.py
empower_core/envmanager/env.py
empower_core/envmanager/envhandler.py
empower_core/envmanager/envmanager.py
empower_core/envmanager/workercallbackshandler.py
empower_core/envmanager/workershandler.py
empower_core/projectsmanager/__init__.py
empower_core/projectsmanager/appcallbackhandler.py
empower_core/projectsmanager/appshandler.py
empower_core/projectsmanager/cataloghandler.py
empower_core/projectsmanager/project.py
empower_core/projectsmanager/projectshandler.py
empower_core/projectsmanager/projectsmanager.py
empower_core/timeseriesmanager/__init__.py
empower_core/timeseriesmanager/timeseriesmanager.py
empower_core-1.0.13.dist-info/LICENSE
empower_core-1.0.13.dist-info/METADATA
empower_core-1.0.13.dist-info/WHEEL
empower_core-1.0.13.dist-info/top_level.txt
empower_core-1.0.13.dist-info/RECORD
