Metadata-Version: 2.1
Name: empower-core
Version: 1.0.13
Summary: The EmPOWER core library
Home-page: http://5g-empower.github.io/
Author: Roberto Riggio
Author-email: roberto.riggio@gmail.com
License: UNKNOWN
Platform: UNKNOWN
Classifier: Programming Language :: Python :: 3
Classifier: License :: OSI Approved :: Apache Software License
Classifier: Operating System :: OS Independent
Requires-Python: >=3.7
